{"experiment_id": "5c59f15f", "status": "complete", "current_round": 1, "rounds": 1, "days": [{"day": 0, "seed": 42, "policies": {"BANK_A": {"version": "2.0", "policy_id": "default_fifo", "parameters": {"initial_liquidity_fraction": 0.5}, "bank_tree": {"type": "action", "node_id": "bank_root", "action": "NoAction"}, "payment_tree": {"type": "action", "node_id": "pay_root", "action": "Release"}}, "BANK_B": {"version": "2.0", "policy_id": "default_fifo", "parameters": {"initial_liquidity_fraction": 0.5}, "bank_tree": {"type": "action", "node_id": "bank_root", "action": "NoAction"}, "payment_tree": {"type": "action", "node_id": "pay_root", "action": "Release"}}}, "costs": {"BANK_A": {"liquidity_cost": 999, "delay_cost": 0, "penalty_cost": 0, "total": 49950}, "BANK_B": {"liquidity_cost": 999, "delay_cost": 0, "penalty_cost": 0, "total": 49950}}, "events": [], "balance_history": {"BANK_A": [502341, 545641, 27778], "BANK_B": [497659, 454359, -27778]}, "total_cost": 99900, "per_agent_costs": {"BANK_A": 49950, "BANK_B": 49950}, "num_ticks": 3, "optimized": false, "optimization_failed": false, "event_count": 99, "event_summary": {"BANK_A": {"arrivals": 10, "settled": 10}, "BANK_B": {"arrivals": 11, "settled": 11}}, "total_arrivals": 21, "total_settled": 21, "has_prompts": false, "prompt_agents": [], "settlement": {"system": {"settled": 21, "total": 21, "rate": 1.0}, "per_bank": {"BANK_A": {"settled": 10, "total": 10, "rate": 1.0}, "BANK_B": {"settled": 11, "total": 11, "rate": 1.0}}}}], "policies": {}, "policy_history": [], "costs": {}, "optimization_summary": {"total": 0, "optimized": 0, "failed": 0, "failed_days": []}, "quality": "clean"}