{
  "policy_id": "iter_002_incremental_low_cost",
  "version": "2.0",
  "description": "Incremental tweak of baseline policy; slightly more conservative liquidity buffer and same urgency to preserve 100% settlement while aiming to reduce overdraft cost.",
  "parameters": {
    "urgency_threshold": 3.0,
    "liquidity_buffer": 1.1,
    "initial_collateral_fraction": 0.25,
    "eod_urgency_boost": 2.0
  },
  "payment_tree": {
    "type": "condition",
    "condition": {
      "op": "<=",
      "left": {
        "field": "ticks_to_deadline"
      },
      "right": {
        "param": "urgency_threshold"
      }
    },
    "on_true": {
      "type": "action",
      "action": "Release",
      "node_id": "P2_release_urgent",
      "description": "Release urgent payments regardless of liquidity buffer check."
    },
    "on_false": {
      "type": "condition",
      "condition": {
        "op": ">=",
        "left": {
          "field": "effective_liquidity"
        },
        "right": {
          "compute": {
            "op": "*",
            "left": {
              "field": "remaining_amount"
            },
            "right": {
              "param": "liquidity_buffer"
            }
          }
        }
      },
      "on_true": {
        "type": "action",
        "action": "Release",
        "node_id": "P4_release_non_urgent_with_buffer",
        "description": "Release when there is enough effective liquidity including the buffer."
      },
      "on_false": {
        "type": "action",
        "action": "Hold",
        "node_id": "P5_hold_non_urgent_liquidity_tight",
        "description": "Hold non-urgent payments when liquidity is tight to avoid overdraft cost."
      },
      "node_id": "P3_has_sufficient_liquidity",
      "description": "For non-urgent payments, require effective_liquidity to cover amount times a safety buffer to limit overdrafts."
    },
    "node_id": "P1_is_urgent",
    "description": "Urgent payments (close to deadline) always released to avoid deadline penalties and end-of-day risk."
  },
  "bank_tree": {
    "type": "action",
    "action": "NoAction",
    "node_id": "B1_noop_bank",
    "description": "No dynamic bank-level state or release budget logic for this simple scenario."
  },
  "strategic_collateral_tree": {
    "type": "action",
    "action": "HoldCollateral",
    "node_id": "SC1_hold_all_collateral",
    "description": "Do not actively post or withdraw collateral in this low-complexity scenario; rely on existing liquidity."
  },
  "end_of_tick_collateral_tree": {
    "type": "action",
    "action": "HoldCollateral",
    "node_id": "EC1_hold_eod_collateral",
    "description": "End-of-tick: keep collateral position unchanged to avoid collateral cost churn."
  }
}